pyxios/__init__.py
pyxios/pyxios.py
pyxios-1.0.2.dist-info/LICENSE
pyxios-1.0.2.dist-info/METADATA
pyxios-1.0.2.dist-info/WHEEL
pyxios-1.0.2.dist-info/top_level.txt
pyxios-1.0.2.dist-info/RECORD
