Metadata-Version: 2.1
Name: pyxios
Version: 1.0.2
Summary: UNKNOWN
Home-page: https://github.com/gssbruno/pyxios
Author: Bruno Santos
Author-email: b.g.santos@outlook.com
License: UNKNOWN
Platform: UNKNOWN
License-File: LICENSE
